owasp/untrust/boxedpath/__init__.py
owasp/untrust/boxedpath/boxedpath.py
owasp_untrust_boxedpath-0.1.0.dist-info/licenses/LICENSE
owasp_untrust_boxedpath-0.1.0.dist-info/METADATA
owasp_untrust_boxedpath-0.1.0.dist-info/WHEEL
owasp_untrust_boxedpath-0.1.0.dist-info/top_level.txt
owasp_untrust_boxedpath-0.1.0.dist-info/RECORD
