Metadata-Version: 2.4
Name: owasp.untrust.boxedpath
Version: 0.1.0
Summary: Secure path sandboxing for untrusted environments
Author-email: Yariv Tal <yariv@owasp.org>
License-Expression: Apache-2.0
Requires-Python: >=3.8
License-File: LICENSE
Dynamic: license-file
